utitools/__init__.py
utitools/platform.py
utitools/uti.csv
utitools/uti.py
utitools/uti_tree.json
utitools-0.2.0.dist-info/LICENSE
utitools-0.2.0.dist-info/WHEEL
utitools-0.2.0.dist-info/METADATA
utitools-0.2.0.dist-info/RECORD
